Workbook

Sheet ReadMe
B2: ACOB — AI Choice. One Bite.
B3: Investor Model — Projectboca.com · drafted July 18, 2026 · all product/pricing inputs are founder-editable assumptions
B5: How to use this workbook
B6: Assumptions | C6: The control panel. Every blue cell is an editable input; yellow cells are the highest-leverage ones. Everything else recalculates.
B7: MarketSizing | C7: TAM / SAM / SOM two ways: decision-moments and dollars. Formula-driven from Assumptions.
B8: UnitEconomics | C8: Per-MAU contribution and payback (consumer side); LTV, CAC, LTV:CAC (restaurant side).
B9: Model | C9: 36-month operating model: users, partners, three revenue engines, COGS, S&M, EBITDA, cumulative cash need.
B10: Summary | C10: Annual roll-up of the monthly model, plus a scenario sensitivity table (incl. "E1 = $0" stress case).
B11: KPIs | C11: The headline metrics an investor asks for first: break-even month, peak burn, exit ARR, LTV:CAC.
B13: Color legend
B14: Blue text | C14: Hardcoded input — edit these
B15: Blue text on yellow | C15: Key assumption — highest sensitivity, edit first
B16: Black text | C16: Formula within the sheet — do not overwrite
B17: Green text | C17: Link to another sheet — do not overwrite
B19: Sources & caveats
C20: Market stats cited on Assumptions (NRA 2026 State of the Industry; SocialPilot review stats; OnePoll/Seated surveys).
C21: All ACOB-specific figures (prices, conversion, growth) are illustrative working assumptions from the founder session — not measured data.
C22: This is a planning model, not financial advice or a forecast of actual results.

Sheet Assumptions
B2: Assumptions — the control panel
B3: Edit blue cells. Yellow = highest-leverage. Column D names the source or basis.
B5: Market (US)
B6: US adults (18+) | C6: 262000000 | D6: Census-order estimate — verify against current ACS data
B7: % of adults dining/ordering out regularly | C7: 0.85 | D7: Estimate — NRA consumer surveys directionally support high-80s engagement
B8: Dine-out/order-out decisions per adult per week | C8: 3 | D8: Survey-order estimate (Seated/OnePoll deliberation studies) — verify
B9: % of diners consulting reviews before choosing | C9: 0.94 | D9: SocialPilot online-review statistics, 2026
B10: US restaurant & foodservice sales, 2026 ($) | C10: 1550000000000 | D10: National Restaurant Association, 2026 State of the Industry
B11: Restaurant marketing spend, % of sales | C11: 0.03 | D11: Industry rule of thumb 3–6%; conservative end used
B12: Digital local-discovery share of marketing | C12: 0.4 | D12: Assumption
B13: Obtainable share within 3 years (SOM) | C13: 0.001 | D13: Assumption — launch-metro wedge
B15: Engine 1 — Consumer (app + premium)
B16: MAU, month 1 (launch metro) | C16: 2000 | D16: Founder assumption — post real-catalog launch
B17: MAU growth, % MoM, Year 1 | C17: 0.2 | D17: Assumption
B18: MAU growth, % MoM, Year 2 | C18: 0.12 | D18: Assumption
B19: MAU growth, % MoM, Year 3 | C19: 0.08 | D19: Assumption
B20: Free → premium conversion (% of MAU) | C20: 0.03 | D20: Assumption — consumer-app norm 2–5%
B21: Premium price, $/month | C21: 4.99 | D21: Founder assumption
B22: Premium monthly churn | C22: 0.05 | D22: Assumption
B23: Consumer CAC, $ per new MAU | C23: 2.5 | D23: Assumption — paid + organic blend
B25: Engine 2 — Restaurants (Menu Intelligence)
B26: Partner restaurants, month 1 | C26: 10 | D26: Hand-onboarded at launch
B27: Net new partners per month, Year 1 | C27: 8 | D27: Assumption — founder-led sales
B28: Net new partners per month, Year 2 | C28: 20 | D28: Assumption — first sales hire
B29: Net new partners per month, Year 3 | C29: 40 | D29: Assumption — second metro
B30: Menu Intelligence fee, $/month | C30: 99 | D30: Founder assumption — anti-Groupon: analytics, never placement
B31: Partner monthly churn | C31: 0.03 | D31: Assumption
B32: Partner CAC (sales + onboarding), $ | C32: 300 | D32: Assumption
B33: Dish photography per new partner, $ (COGS) | C33: 150 | D33: Assumption — card quality is product quality
B35: Engine 3 — Decided-diner handoff
B36: Handoffs per MAU per month | C36: 0.6 | D36: Assumption — completed reveals routed to maps/pickup/delivery
B37: Fee per handoff, $ | C37: 1 | D37: Assumption — delivery/reservation affiliate norms
B39: Costs
B40: Hosting + data cost per MAU per month, $ | C40: 0.15 | D40: Assumption — Vercel/db/API at scale
B41: Payment processing, % of subscription revenue | C41: 0.029 | D41: Stripe-order pricing
B42: Fixed opex per month, Year 1, $ | C42: 25000 | D42: Assumption — founder + 2 contractors + tools
B43: Fixed opex per month, Year 2, $ | C43: 45000 | D43: Assumption — +2 hires
B44: Fixed opex per month, Year 3, $ | C44: 70000 | D44: Assumption — team of ~7

Sheet MarketSizing
B2: Market sizing — moments and money
B3: All rows are formulas driven by the Assumptions tab.
B5: By moments (the story)
B6: US adults | C6: =Assumptions!C6 -> 262000000
B7: Adults dining/ordering out regularly | C7: =C6*Assumptions!C7 -> 222700000
B8: "Where should we eat?" moments per year | C8: =C7*Assumptions!C8*52 -> 34741200000 | D8: ≈ 35 billion at base assumptions
B9: Researched decisions (addressable moments) | C9: =C8*Assumptions!C9 -> 32656728000
B11: By money (the model)
B12: US restaurant & foodservice sales, 2026 | C12: =Assumptions!C10 -> 1550000000000
B13: TAM — restaurant demand-generation spend | C13: =C12*Assumptions!C11 -> 46500000000 | D13: Sales × marketing-spend %
B14: SAM — digital local-discovery spend | C14: =C13*Assumptions!C12 -> 18600000000 | D14: TAM × digital/local share
B15: SOM — obtainable within 3 years | C15: =C14*Assumptions!C13 -> 18600000 | D15: SAM × obtainable share
B17: Consumer layer cross-check
B18: Adults who struggle deciding what to order (79%) | C18: =C6*0.79 -> 206980000 | D18: US Foods survey via KSAT, 2024 — premium audience ceiling

Sheet UnitEconomics
B2: Unit economics
B4: Consumer side — per monthly active user
B5: E1 contribution / MAU / month (conv × price, net of processing) | C5: =Assumptions!C20*Assumptions!C21*(1-Assumptions!C41) -> 0.1453587
B6: E3 contribution / MAU / month (handoffs × fee) | C6: =Assumptions!C36*Assumptions!C37 -> 0.6
B7: Hosting cost / MAU / month | C7: =-Assumptions!C40 -> -0.15
B8: Net contribution / MAU / month | C8: =C5+C6+C7 -> 0.5953587
B9: Consumer CAC per new MAU | C9: =Assumptions!C23 -> 2.5
B10: CAC payback, months | C10: =IF(C8<=0,"n/a",C9/C8) -> 4.1991492 | D10: Consumer-app benchmark: < 12 months is healthy; < 6 strong
B12: Restaurant side — per Menu Intelligence partner
B13: Monthly fee (net of processing) | C13: =Assumptions!C30*(1-Assumptions!C41) -> 96.129
B14: Average lifetime, months (1 ÷ churn) | C14: =IF(Assumptions!C31=0,"n/a",1/Assumptions!C31) -> 33.333333
B15: LTV (net fee × lifetime) | C15: =IF(Assumptions!C31=0,"n/a",C13/Assumptions!C31) -> 3204.3
B16: CAC (sales + onboarding + photography) | C16: =Assumptions!C32+Assumptions!C33 -> 450
B17: LTV : CAC | C17: =IF(C16=0,"n/a",C15/C16) -> 7.1206667 | D17: SaaS benchmark: > 3x healthy, > 4x strong
B18: CAC payback, months | C18: =IF(C13=0,"n/a",C16/C13) -> 4.6812096

Sheet Model
A1: ACOB — 36-month operating model
A2: Month | B2: M1 | C2: M2 | D2: M3 | E2: M4 | F2: M5 | G2: M6 | H2: M7 | I2: M8 | J2: M9 | K2: M10 | L2: M11 | M2: M12 | N2: M13 | O2: M14 | P2: M15 | Q2: M16 | R2: M17 | S2: M18 | T2: M19 | U2: M20 | V2: M21 | W2: M22 | X2: M23 | Y2: M24 | Z2: M25 | AA2: M26 | AB2: M27 | AC2: M28 | AD2: M29 | AE2: M30 | AF2: M31 | AG2: M32 | AH2: M33 | AI2: M34 | AJ2: M35 | AK2: M36
A3: Month # | B3: 1 | C3: =B3+1 -> 2 | D3: =C3+1 -> 3 | E3: =D3+1 -> 4 | F3: =E3+1 -> 5 | G3: =F3+1 -> 6 | H3: =G3+1 -> 7 | I3: =H3+1 -> 8 | J3: =I3+1 -> 9 | ... AK3: =AJ3+1 -> 36
A4: Year | B4: 1 | C4: =IF(C3<=12,1,IF(C3<=24,2,3)) -> 1 | D4: =IF(D3<=12,1,IF(D3<=24,2,3)) -> 1 | E4: =IF(E3<=12,1,IF(E3<=24,2,3)) -> 1 | F4: =IF(F3<=12,1,IF(F3<=24,2,3)) -> 1 | G4: =IF(G3<=12,1,IF(G3<=24,2,3)) -> 1 | H4: =IF(H3<=12,1,IF(H3<=24,2,3)) -> 1 | I4: =IF(I3<=12,1,IF(I3<=24,2,3)) -> 1 | J4: =IF(J3<=12,1,IF(J3<=24,2,3)) -> 1 | ... AK4: =IF(AK3<=12,1,IF(AK3<=24,2,3)) -> 3
A5: Monthly active users (MAU) | B5: =Assumptions!C16 -> 2000 | C5: =B5*(1+IF(C4=1,Assumptions!$C$17,IF(C4=2,Assumptions!$C$18,Assumptions!$C$19))) -> 2400 | D5: =C5*(1+IF(D4=1,Assumptions!$C$17,IF(D4=2,Assumptions!$C$18,Assumptions!$C$19))) -> 2880 | E5: =D5*(1+IF(E4=1,Assumptions!$C$17,IF(E4=2,Assumptions!$C$18,Assumptions!$C$19))) -> 3456 | F5: =E5*(1+IF(F4=1,Assumptions!$C$17,IF(F4=2,Assumptions!$C$18,Assumptions!$C$19))) -> 4147.2 | G5: =F5*(1+IF(G4=1,Assumptions!$C$17,IF(G4=2,Assumptions!$C$18,Assumptions!$C$19))) -> 4976.64 | H5: =G5*(1+IF(H4=1,Assumptions!$C$17,IF(H4=2,Assumptions!$C$18,Assumptions!$C$19))) -> 5971.968 | I5: =H5*(1+IF(I4=1,Assumptions!$C$17,IF(I4=2,Assumptions!$C$18,Assumptions!$C$19))) -> 7166.3616 | J5: =I5*(1+IF(J4=1,Assumptions!$C$17,IF(J4=2,Assumptions!$C$18,Assumptions!$C$19))) -> 8599.6339 | ... AK5: =AJ5*(1+IF(AK4=1,Assumptions!$C$17,IF(AK4=2,Assumptions!$C$18,Assumptions!$C$19))) -> 145789.1
A6: New MAU in month | B6: =B5 -> 2000 | C6: =C5-B5 -> 400 | D6: =D5-C5 -> 480 | E6: =E5-D5 -> 576 | F6: =F5-E5 -> 691.2 | G6: =G5-F5 -> 829.44 | H6: =H5-G5 -> 995.328 | I6: =I5-H5 -> 1194.3936 | J6: =J5-I5 -> 1433.2723 | ... AK6: =AK5-AJ5 -> 10799.192
A7: Premium subscribers | B7: =B5*Assumptions!$C$20 -> 60 | C7: =C5*Assumptions!$C$20 -> 72 | D7: =D5*Assumptions!$C$20 -> 86.4 | E7: =E5*Assumptions!$C$20 -> 103.68 | F7: =F5*Assumptions!$C$20 -> 124.416 | G7: =G5*Assumptions!$C$20 -> 149.2992 | H7: =H5*Assumptions!$C$20 -> 179.15904 | I7: =I5*Assumptions!$C$20 -> 214.99085 | ... AK7: =AK5*Assumptions!$C$20 -> 4373.6729
A8: E1 revenue — consumer premium | B8: =B7*Assumptions!$C$21 -> 299.4 | C8: =C7*Assumptions!$C$21 -> 359.28 | D8: =D7*Assumptions!$C$21 -> 431.136 | E8: =E7*Assumptions!$C$21 -> 517.3632 | F8: =F7*Assumptions!$C$21 -> 620.83584 | G8: =G7*Assumptions!$C$21 -> 745.00301 | H8: =H7*Assumptions!$C$21 -> 894.00361 | I8: =I7*Assumptions!$C$21 -> 1072.8043 | ... AK8: =AK7*Assumptions!$C$21 -> 21824.628
A9: Partner restaurants | B9: =Assumptions!C26 -> 10 | C9: =B9+IF(C4=1,Assumptions!$C$27,IF(C4=2,Assumptions!$C$28,Assumptions!$C$29)) -> 18 | D9: =C9+IF(D4=1,Assumptions!$C$27,IF(D4=2,Assumptions!$C$28,Assumptions!$C$29)) -> 26 | E9: =D9+IF(E4=1,Assumptions!$C$27,IF(E4=2,Assumptions!$C$28,Assumptions!$C$29)) -> 34 | F9: =E9+IF(F4=1,Assumptions!$C$27,IF(F4=2,Assumptions!$C$28,Assumptions!$C$29)) -> 42 | G9: =F9+IF(G4=1,Assumptions!$C$27,IF(G4=2,Assumptions!$C$28,Assumptions!$C$29)) -> 50 | H9: =G9+IF(H4=1,Assumptions!$C$27,IF(H4=2,Assumptions!$C$28,Assumptions!$C$29)) -> 58 | I9: =H9+IF(I4=1,Assumptions!$C$27,IF(I4=2,Assumptions!$C$28,Assumptions!$C$29)) -> 66 | J9: =I9+IF(J4=1,Assumptions!$C$27,IF(J4=2,Assumptions!$C$28,Assumptions!$C$29)) -> 74 | ... AK9: =AJ9+IF(AK4=1,Assumptions!$C$27,IF(AK4=2,Assumptions!$C$28,Assumptions!$C$29)) -> 818
A10: New partners in month | B10: =B9 -> 10 | C10: =C9-B9 -> 8 | D10: =D9-C9 -> 8 | E10: =E9-D9 -> 8 | F10: =F9-E9 -> 8 | G10: =G9-F9 -> 8 | H10: =H9-G9 -> 8 | I10: =I9-H9 -> 8 | J10: =J9-I9 -> 8 | ... AK10: =AK9-AJ9 -> 40
A11: E2 revenue — Menu Intelligence | B11: =B9*Assumptions!$C$30 -> 990 | C11: =C9*Assumptions!$C$30 -> 1782 | D11: =D9*Assumptions!$C$30 -> 2574 | E11: =E9*Assumptions!$C$30 -> 3366 | F11: =F9*Assumptions!$C$30 -> 4158 | G11: =G9*Assumptions!$C$30 -> 4950 | H11: =H9*Assumptions!$C$30 -> 5742 | I11: =I9*Assumptions!$C$30 -> 6534 | ... AK11: =AK9*Assumptions!$C$30 -> 80982
A12: Decided-diner handoffs | B12: =B5*Assumptions!$C$36 -> 1200 | C12: =C5*Assumptions!$C$36 -> 1440 | D12: =D5*Assumptions!$C$36 -> 1728 | E12: =E5*Assumptions!$C$36 -> 2073.6 | F12: =F5*Assumptions!$C$36 -> 2488.32 | G12: =G5*Assumptions!$C$36 -> 2985.984 | H12: =H5*Assumptions!$C$36 -> 3583.1808 | I12: =I5*Assumptions!$C$36 -> 4299.817 | ... AK12: =AK5*Assumptions!$C$36 -> 87473.457
A13: E3 revenue — handoff fees | B13: =B12*Assumptions!$C$37 -> 1200 | C13: =C12*Assumptions!$C$37 -> 1440 | D13: =D12*Assumptions!$C$37 -> 1728 | E13: =E12*Assumptions!$C$37 -> 2073.6 | F13: =F12*Assumptions!$C$37 -> 2488.32 | G13: =G12*Assumptions!$C$37 -> 2985.984 | H13: =H12*Assumptions!$C$37 -> 3583.1808 | I13: =I12*Assumptions!$C$37 -> 4299.817 | ... AK13: =AK12*Assumptions!$C$37 -> 87473.457
A14: Total revenue | B14: =B8+B11+B13 -> 2489.4 | C14: =C8+C11+C13 -> 3581.28 | D14: =D8+D11+D13 -> 4733.136 | E14: =E8+E11+E13 -> 5956.9632 | F14: =F8+F11+F13 -> 7267.1558 | G14: =G8+G11+G13 -> 8680.987 | H14: =H8+H11+H13 -> 10219.184 | I14: =I8+I11+I13 -> 11906.621 | ... AK14: =AK8+AK11+AK13 -> 190280.08
A15: COGS (hosting + photography + processing) | B15: =B5*Assumptions!$C$40+B10*Assumptions!$C$33+(B8+B11)*Assumptions!$C$41 -> 1837.3926 | C15: =C5*Assumptions!$C$40+C10*Assumptions!$C$33+(C8+C11)*Assumptions!$C$41 -> 1622.0971 | D15: =D5*Assumptions!$C$40+D10*Assumptions!$C$33+(D8+D11)*Assumptions!$C$41 -> 1719.1489 | E15: =E5*Assumptions!$C$40+E10*Assumptions!$C$33+(E8+E11)*Assumptions!$C$41 -> 1831.0175 | F15: =F5*Assumptions!$C$40+F10*Assumptions!$C$33+(F8+F11)*Assumptions!$C$41 -> 1960.6662 | G15: =G5*Assumptions!$C$40+G10*Assumptions!$C$33+(G8+G11)*Assumptions!$C$41 -> 2111.6511 | H15: =H5*Assumptions!$C$40+H10*Assumptions!$C$33+(H8+H11)*Assumptions!$C$41 -> 2288.2393 | I15: =I5*Assumptions!$C$40+I10*Assumptions!$C$33+(I8+I11)*Assumptions!$C$41 -> 2495.5516 | ... AK15: =AK5*Assumptions!$C$40+AK10*Assumptions!$C$33+(AK8+AK11)*Assumptions!$C$41 -> 30849.756
A16: Gross profit | B16: =B14-B15 -> 652.0074 | C16: =C14-C15 -> 1959.1829 | D16: =D14-D15 -> 3013.9871 | E16: =E14-E15 -> 4125.9457 | F16: =F14-F15 -> 5306.4896 | G16: =G14-G15 -> 6569.3359 | H16: =H14-H15 -> 7930.9451 | I16: =I14-I15 -> 9411.0697 | ... AK16: =AK14-AK15 -> 159430.33
A17: Gross margin % | B17: =IF(B14=0,0,B16/B14) -> 0.26191347 | C17: =IF(C14=0,0,C16/C14) -> 0.54706219 | D17: =IF(D14=0,0,D16/D14) -> 0.63678438 | E17: =IF(E14=0,0,E16/E14) -> 0.69262568 | F17: =IF(F14=0,0,F16/F14) -> 0.73020171 | G17: =IF(G14=0,0,G16/G14) -> 0.75674989 | H17: =IF(H14=0,0,H16/H14) -> 0.77608396 | I17: =IF(I14=0,0,I16/I14) -> 0.7904064 | ... AK17: =IF(AK14=0,0,AK16/AK14) -> 0.83787186
A18: Sales & marketing (CAC spend) | B18: =B6*Assumptions!$C$23+B10*Assumptions!$C$32 -> 8000 | C18: =C6*Assumptions!$C$23+C10*Assumptions!$C$32 -> 3400 | D18: =D6*Assumptions!$C$23+D10*Assumptions!$C$32 -> 3600 | E18: =E6*Assumptions!$C$23+E10*Assumptions!$C$32 -> 3840 | F18: =F6*Assumptions!$C$23+F10*Assumptions!$C$32 -> 4128 | G18: =G6*Assumptions!$C$23+G10*Assumptions!$C$32 -> 4473.6 | H18: =H6*Assumptions!$C$23+H10*Assumptions!$C$32 -> 4888.32 | I18: =I6*Assumptions!$C$23+I10*Assumptions!$C$32 -> 5385.984 | ... AK18: =AK6*Assumptions!$C$23+AK10*Assumptions!$C$32 -> 38997.981
A19: Fixed operating expenses | B19: =IF(B4=1,Assumptions!$C$42,IF(B4=2,Assumptions!$C$43,Assumptions!$C$44)) -> 25000 | C19: =IF(C4=1,Assumptions!$C$42,IF(C4=2,Assumptions!$C$43,Assumptions!$C$44)) -> 25000 | D19: =IF(D4=1,Assumptions!$C$42,IF(D4=2,Assumptions!$C$43,Assumptions!$C$44)) -> 25000 | E19: =IF(E4=1,Assumptions!$C$42,IF(E4=2,Assumptions!$C$43,Assumptions!$C$44)) -> 25000 | F19: =IF(F4=1,Assumptions!$C$42,IF(F4=2,Assumptions!$C$43,Assumptions!$C$44)) -> 25000 | G19: =IF(G4=1,Assumptions!$C$42,IF(G4=2,Assumptions!$C$43,Assumptions!$C$44)) -> 25000 | H19: =IF(H4=1,Assumptions!$C$42,IF(H4=2,Assumptions!$C$43,Assumptions!$C$44)) -> 25000 | I19: =IF(I4=1,Assumptions!$C$42,IF(I4=2,Assumptions!$C$43,Assumptions!$C$44)) -> 25000 | ... AK19: =IF(AK4=1,Assumptions!$C$42,IF(AK4=2,Assumptions!$C$43,Assumptions!$C$44)) -> 70000
A20: EBITDA | B20: =B16-B18-B19 -> -32347.993 | C20: =C16-C18-C19 -> -26440.817 | D20: =D16-D18-D19 -> -25586.013 | E20: =E16-E18-E19 -> -24714.054 | F20: =F16-F18-F19 -> -23821.51 | G20: =G16-G18-G19 -> -22904.264 | H20: =H16-H18-H19 -> -21957.375 | I20: =I16-I18-I19 -> -20974.914 | ... AK20: =AK16-AK18-AK19 -> 50432.348
A21: Cumulative EBITDA (cash need proxy) | B21: =B20 -> -32347.993 | C21: =B21+C20 -> -58788.81 | D21: =C21+D20 -> -84374.823 | E21: =D21+E20 -> -109088.88 | F21: =E21+F20 -> -132910.39 | G21: =F21+G20 -> -155814.65 | H21: =G21+H20 -> -177772.03 | I21: =H21+I20 -> -198746.94 | J21: =I21+J20 -> -218696.71 | ... AK21: =AJ21+AK20 -> -404755.16

Sheet Summary
B2: Annual summary
C4: Year 1 | D4: Year 2 | E4: Year 3
B5: E1 — consumer premium | C5: =SUM(Model!B8:M8) -> 11850.402 | D5: =SUM(Model!N8:Y8) -> 60128.066 | E5: =SUM(Model!Z8:AK8) -> 177629.86
B6: E2 — Menu Intelligence | C6: =SUM(Model!B11:M11) -> 64152 | D6: =SUM(Model!N11:Y11) -> 270864 | E6: =SUM(Model!Z11:AK11) -> 710424
B7: E3 — handoff fees | C7: =SUM(Model!B13:M13) -> 47496.603 | D7: =SUM(Model!N13:Y13) -> 240994.25 | E7: =SUM(Model!Z13:AK13) -> 711943.34
B8: Total revenue | C8: =SUM(Model!B14:M14) -> 123499.01 | D8: =SUM(Model!N14:Y14) -> 571986.32 | E8: =SUM(Model!Z14:AK14) -> 1599997.2
B9: Gross profit | C9: =SUM(Model!B16:M16) -> 94720.785 | D9: =SUM(Model!N16:Y16) -> 466138.99 | E9: =SUM(Model!Z16:AK16) -> 1324257.8
B10: Gross margin % | C10: =IF(C8=0,0,C9/C8) -> 0.7669761 | D10: =IF(D8=0,0,D9/D8) -> 0.81494779 | E10: =IF(E8=0,0,E9/E8) -> 0.82766258
B11: Sales & marketing | C11: =SUM(Model!B18:M18) -> 66550.419 | D11: =SUM(Model!N18:Y18) -> 179586.72 | E11: =SUM(Model!Z18:AK18) -> 363735.6
B12: Fixed opex | C12: =SUM(Model!B19:M19) -> 300000 | D12: =SUM(Model!N19:Y19) -> 540000 | E12: =SUM(Model!Z19:AK19) -> 840000
B13: EBITDA | C13: =SUM(Model!B20:M20) -> -271829.63 | D13: =SUM(Model!N20:Y20) -> -253447.73 | E13: =SUM(Model!Z20:AK20) -> 120522.21
B14: Exit MAU (month 12/24/36) | C14: =Model!M5 -> 14860.167 | D14: =Model!Y5 -> 57894.855 | E14: =Model!AK5 -> 145789.1
B15: Exit partner restaurants | C15: =Model!M9 -> 98 | D15: =Model!Y9 -> 338 | E15: =Model!AK9 -> 818
B16: Exit ARR run-rate (exit month × 12) | C16: =Model!M14*12 -> 250112.01 | D16: =Model!Y14*12 -> 922389.28 | E16: =Model!AK14*12 -> 2283361
B19: Scenario sensitivity — Year-1 exit month (M12) revenue run-rate
B20: Drivers are standalone blue inputs per scenario; formulas below recompute M12 monthly revenue from scratch.
C21: Conservative | D21: Base | E21: Aggressive | F21: E1 = $0 stress
B22: MAU growth % MoM (Y1) | C22: 0.12 | D22: 0.2 | E22: 0.28 | F22: 0.2
B23: Premium conversion % | C23: 0.02 | D23: 0.03 | E23: 0.05 | F23: 0.03
B24: Partner restaurants at M12 | C24: 60 | D24: 98 | E24: 140 | F24: 98
B25: E1 engine on? (1/0) | C25: 1 | D25: 1 | E25: 1 | F25: 0
B26: M12 MAU | C26: =Assumptions!$C$16*(1+C22)^11 -> 6957.1 | D26: =Assumptions!$C$16*(1+D22)^11 -> 14860.167 | E26: =Assumptions!$C$16*(1+E22)^11 -> 30223.145 | F26: =Assumptions!$C$16*(1+F22)^11 -> 14860.167
B27: M12 monthly revenue | C27: =C26*C23*Assumptions!$C$21*C25+C24*Assumptions!$C$30+C26*Assumptions!$C$36*Assumptions!$C$37 -> 10808.579 | D27: =D26*D23*Assumptions!$C$21*D25+D24*Assumptions!$C$30+D26*Assumptions!$C$36*Assumptions!$C$37 -> 20842.668 | E27: =E26*E23*Assumptions!$C$21*E25+E24*Assumptions!$C$30+E26*Assumptions!$C$36*Assumptions!$C$37 -> 39534.562 | F27: =F26*F23*Assumptions!$C$21*F25+F24*Assumptions!$C$30+F26*Assumptions!$C$36*Assumptions!$C$37 -> 18618.1
B28: Implied exit ARR | C28: =C27*12 -> 129702.94 | D28: =D27*12 -> 250112.01 | E28: =E27*12 -> 474414.75 | F28: =F27*12 -> 223417.21
B30: Note: the "E1 = $0" case answers the diligence question "what if consumers never pay?" — E2 + E3 still carry the model.

Sheet KPIs
B2: KPI dashboard — what an investor asks first
B4: EBITDA break-even month | C4: =IF(SUMPRODUCT(--(Model!$B$21:$AK$21<=0))>=36,"Beyond M36",SUMPRODUCT(--(Model!$B$21:$AK$21<=0))+1) -> Beyond M36 | D4: First month cumulative EBITDA turns positive
B5: Peak cumulative burn (min cumulative EBITDA) | C5: =MIN(Model!$B$21:$AK$21) -> -594683.05 | D5: Proxy for minimum capital required (pre-buffer)
B6: Implied raise (peak burn × 1.4 buffer) | C6: =-MIN(Model!$B$21:$AK$21)*1.4 -> 832556.28 | D6: 40% buffer over modeled need
B7: Year-3 exit ARR run-rate | C7: =Model!AK14*12 -> 2283361 | D7: Exit month × 12
B8: Year-3 exit MAU | C8: =Model!AK5 -> 145789.1
B9: Year-3 exit partner restaurants | C9: =Model!AK9 -> 818
B10: Year-3 gross margin % | C10: =Summary!E10 -> 0.82766258
B11: Restaurant LTV : CAC | C11: =UnitEconomics!C17 -> 7.1206667 | D11: Benchmark: > 3x
B12: Consumer CAC payback, months | C12: =UnitEconomics!C10 -> 4.1991492 | D12: Benchmark: < 12
B13: E2 + E3 share of Year-3 revenue | C13: =IF(Summary!E8=0,0,(Summary!E6+Summary!E7)/Summary!E8) -> 0.88898114 | D13: Shows the model does not lean on consumer subscriptions
B15: Product KPIs to report alongside financials (from app telemetry once live):
B16: · Median time-to-decision (target < 60s)
B17: · Lightning Round completion rate (target > 60%)
B18: · Reveal-to-action rate (directions/order tapped)
B19: · D30 retention; sessions per user per week
